booster_wrappers/__init__.py
booster_wrappers/version.py
booster_wrappers-0.0.3.dist-info/METADATA
booster_wrappers-0.0.3.dist-info/WHEEL
booster_wrappers-0.0.3.dist-info/top_level.txt
booster_wrappers-0.0.3.dist-info/RECORD
